[
  {
    "title": "关于对ROHAENI RINI等2人所持居留许可宣布作废的公告",
    "link": "http://hengqin.gd.gov.cn/zwgk/tzgg/content/post_4741536.html",
    "pubDate": "2025-07-08"
  },
  {
    "title": "关于公布固定式交通技术监控设备设置地点及查处的违法行为类别的通告",
    "link": "http://hengqin.gd.gov.cn/zwgk/tzgg/content/post_4738644.html",
    "pubDate": "2025-07-02"
  },
  {
    "title": "关于启用横琴粤澳深度合作区综治中心印章的通告",
    "link": "http://hengqin.gd.gov.cn/zwgk/tzgg/content/post_4736744.html",
    "pubDate": "2025-06-30"
  },
  {
    "title": "横琴粤澳深度合作区公安局2025年面向公安院校招警拟录用人员公示",
    "link": "http://hengqin.gd.gov.cn/zwgk/tzgg/content/post_4725775.html",
    "pubDate": "2025-06-17"
  },
  {
    "title": "横琴粤澳深度合作区公安局2025年考试录用公务员拟录用人员公示",
    "link": "http://hengqin.gd.gov.cn/zwgk/tzgg/content/post_4725680.html",
    "pubDate": "2025-06-17"
  },
  {
    "title": "横琴粤澳深度合作区2024年“6·30”助力乡村振兴活动社会捐款接收情况公告",
    "link": "http://hengqin.gd.gov.cn/zwgk/tzgg/content/post_4723353.html",
    "pubDate": "2025-06-10"
  },
  {
    "title": "关于对MOROZOV ALEKSEI等3人所持居留许可宣布作废的公告",
    "link": "http://hengqin.gd.gov.cn/zwgk/tzgg/content/post_4716269.html",
    "pubDate": "2025-05-26"
  },
  {
    "title": "中共广东省委横琴粤澳深度合作区工作委员会2025年度选调生拟录用人员公示",
    "link": "http://hengqin.gd.gov.cn/zwgk/tzgg/content/post_4712267.html",
    "pubDate": "2025-05-17"
  },
  {
    "title": "关于对合作区2024年度社会工作者职业水平评价奖励拟发放人员名单的公示",
    "link": "http://hengqin.gd.gov.cn/attachment/0/579/579870/4709663.pdf",
    "pubDate": "2025-05-12"
  },
  {
    "title": "横琴粤澳深度合作区公安局关于居住证申领工作的规定",
    "link": "http://hengqin.gd.gov.cn/zwgk/tzgg/content/post_4708115.html",
    "pubDate": "2025-05-08"
  },
  {
    "title": "横琴粤澳深度合作区备案人民调解组织及人民调解员名册的公示",
    "link": "http://hengqin.gd.gov.cn/zwgk/tzgg/content/post_4707876.html",
    "pubDate": "2025-05-08"
  },
  {
    "title": "关于对UKOLOVA VERONIKA等3人所持居留许可宣布作废的公告",
    "link": "http://hengqin.gd.gov.cn/zwgk/tzgg/content/post_4697180.html",
    "pubDate": "2025-04-15"
  },
  {
    "title": "横琴粤澳深度合作区备案人民调解组织及人民调解员名册的公示",
    "link": "http://hengqin.gd.gov.cn/zwgk/tzgg/content/post_4687387.html",
    "pubDate": "2025-03-26"
  },
  {
    "title": "关于做好2024年度横琴粤澳深度合作区社会组织年度工作报告的通知",
    "link": "http://hengqin.gd.gov.cn/zwgk/tzgg/content/post_4683263.html",
    "pubDate": "2025-03-19"
  },
  {
    "title": "横琴粤澳深度合作区法律援助机构2024年度法律援助信息公示",
    "link": "http://hengqin.gd.gov.cn/zwgk/tzgg/content/post_4682890.html",
    "pubDate": "2025-03-18"
  },
  {
    "title": "广东省2025年度选调优秀大学毕业生省委横琴工委职位体检有关事项公告",
    "link": "http://hengqin.gd.gov.cn/zwgk/tzgg/content/post_4675084.html",
    "pubDate": "2025-03-03"
  },
  {
    "title": "关于横琴粤澳深度合作区婚姻登记处搬迁的通告",
    "link": "http://hengqin.gd.gov.cn/zwgk/tzgg/content/post_4644290.html",
    "pubDate": "2025-01-03"
  },
  {
    "title": "关于规范使用“横琴粤澳深度合作区”名称的通告",
    "link": "http://hengqin.gd.gov.cn/zwgk/tzgg/content/post_4638952.html",
    "pubDate": "2025-01-02"
  },
  {
    "title": "关于横琴粤澳深度合作区备案人民调解组织及其人民调解员名单的公示",
    "link": "http://hengqin.gd.gov.cn/zwgk/tzgg/content/post_4640392.html",
    "pubDate": "2024-12-27"
  },
  {
    "title": "关于公布广东省人民政府横琴粤澳深度合作区工作办公室权责清单（2024年）的通告",
    "link": "http://hengqin.gd.gov.cn/zwgk/tzgg/content/post_4638496.html",
    "pubDate": "2024-12-24"
  }
]